attributable/__init__.py
attributable-0.0.1.dist-info/METADATA
attributable-0.0.1.dist-info/WHEEL
attributable-0.0.1.dist-info/top_level.txt
attributable-0.0.1.dist-info/RECORD
