Metadata-Version: 2.1
Name: attributable
Version: 0.0.1
Summary: attributable helps make LLM generation more verifiable
Author-email: Shannon Zejiang Shen <zejiangshen@gmail.com>, Lucas Torroba Hennigen <lucasfth@gmail.com>
Classifier: Programming Language :: Python :: 3
Classifier: License :: OSI Approved :: MIT License
Classifier: Operating System :: OS Independent
Requires-Python: >=3.6
